[{"id":1,"isim":"Sofia","cinsiyet":"Female","yas":54},
{"id":2,"isim":"Nadean","cinsiyet":"Female","yas":29},
{"id":3,"isim":"Edgardo","cinsiyet":"Male","yas":67},
{"id":4,"isim":"Vonny","cinsiyet":"Female","yas":59},
{"id":5,"isim":"Hercules","cinsiyet":"Male","yas":62},
{"id":6,"isim":"Lanny","cinsiyet":"Male","yas":65},
{"id":7,"isim":"Norris","cinsiyet":"Male","yas":19},
{"id":8,"isim":"Karia","cinsiyet":"Female","yas":51},
{"id":9,"isim":"Korrie","cinsiyet":"Female","yas":37},
{"id":10,"isim":"Hallie","cinsiyet":"Female","yas":54},
{"id":11,"isim":"Aidan","cinsiyet":"Female","yas":31},
{"id":12,"isim":"Lotte","cinsiyet":"Female","yas":60},
{"id":13,"isim":"Zora","cinsiyet":"Female","yas":28},
{"id":14,"isim":"Odelinda","cinsiyet":"Female","yas":46},
{"id":15,"isim":"Basilius","cinsiyet":"Male","yas":51},
{"id":16,"isim":"Irena","cinsiyet":"Female","yas":52},
{"id":17,"isim":"Vite","cinsiyet":"Male","yas":68},
{"id":18,"isim":"Ave","cinsiyet":"Male","yas":47},
{"id":19,"isim":"Vassili","cinsiyet":"Male","yas":25},
{"id":20,"isim":"Bastien","cinsiyet":"Male","yas":62},
{"id":21,"isim":"Ola","cinsiyet":"Female","yas":23},
{"id":22,"isim":"Meryl","cinsiyet":"Male","yas":23},
{"id":23,"isim":"Nikki","cinsiyet":"Male","yas":14},
{"id":24,"isim":"Joy","cinsiyet":"Female","yas":59},
{"id":25,"isim":"Nikola","cinsiyet":"Male","yas":38},
{"id":26,"isim":"Prent","cinsiyet":"Male","yas":29},
{"id":27,"isim":"Amara","cinsiyet":"Female","yas":38},
{"id":28,"isim":"Honor","cinsiyet":"Female","yas":15},
{"id":29,"isim":"Monique","cinsiyet":"Female","yas":56},
{"id":30,"isim":"Fae","cinsiyet":"Female","yas":61},
{"id":31,"isim":"Emilia","cinsiyet":"Female","yas":69},
{"id":32,"isim":"Marley","cinsiyet":"Female","yas":56},
{"id":33,"isim":"Bambie","cinsiyet":"Female","yas":27},
{"id":34,"isim":"Dredi","cinsiyet":"Female","yas":48},
{"id":35,"isim":"Mable","cinsiyet":"Female","yas":29},
{"id":36,"isim":"Dorelle","cinsiyet":"Female","yas":43},
{"id":37,"isim":"Nonna","cinsiyet":"Female","yas":54},
{"id":38,"isim":"Algernon","cinsiyet":"Male","yas":20},
{"id":39,"isim":"Antone","cinsiyet":"Male","yas":19},
{"id":40,"isim":"Lyle","cinsiyet":"Male","yas":27},
{"id":41,"isim":"Corina","cinsiyet":"Female","yas":43},
{"id":42,"isim":"Homer","cinsiyet":"Male","yas":24},
{"id":43,"isim":"Sargent","cinsiyet":"Male","yas":11},
{"id":44,"isim":"Marge","cinsiyet":"Female","yas":67},
{"id":45,"isim":"Jessey","cinsiyet":"Male","yas":33},
{"id":46,"isim":"Paloma","cinsiyet":"Female","yas":52},
{"id":47,"isim":"Perice","cinsiyet":"Male","yas":51},
{"id":48,"isim":"Joe","cinsiyet":"Male","yas":59},
{"id":49,"isim":"Florri","cinsiyet":"Female","yas":21},
{"id":50,"isim":"Dale","cinsiyet":"Female","yas":18},
{"id":51,"isim":"Maximilianus","cinsiyet":"Male","yas":30},
{"id":52,"isim":"Gilberto","cinsiyet":"Male","yas":10},
{"id":53,"isim":"Kenny","cinsiyet":"Male","yas":57},
{"id":54,"isim":"Izaak","cinsiyet":"Male","yas":18},
{"id":55,"isim":"Kitty","cinsiyet":"Female","yas":67},
{"id":56,"isim":"Ber","cinsiyet":"Male","yas":37},
{"id":57,"isim":"Ara","cinsiyet":"Male","yas":13},
{"id":58,"isim":"Tatiania","cinsiyet":"Female","yas":21},
{"id":59,"isim":"Mina","cinsiyet":"Female","yas":57},
{"id":60,"isim":"Antonius","cinsiyet":"Male","yas":64},
{"id":61,"isim":"Bessy","cinsiyet":"Female","yas":50},
{"id":62,"isim":"Homerus","cinsiyet":"Male","yas":58},
{"id":63,"isim":"Lazaro","cinsiyet":"Male","yas":48},
{"id":64,"isim":"Petronilla","cinsiyet":"Female","yas":50},
{"id":65,"isim":"Art","cinsiyet":"Male","yas":39},
{"id":66,"isim":"Garold","cinsiyet":"Male","yas":35},
{"id":67,"isim":"Rafaellle","cinsiyet":"Male","yas":34},
{"id":68,"isim":"Paula","cinsiyet":"Female","yas":19},
{"id":69,"isim":"Alphonso","cinsiyet":"Male","yas":34},
{"id":70,"isim":"Niven","cinsiyet":"Male","yas":55},
{"id":71,"isim":"Othella","cinsiyet":"Female","yas":64},
{"id":72,"isim":"Rodolphe","cinsiyet":"Male","yas":29},
{"id":73,"isim":"Edouard","cinsiyet":"Male","yas":35},
{"id":74,"isim":"Heather","cinsiyet":"Female","yas":52},
{"id":75,"isim":"Marta","cinsiyet":"Female","yas":55},
{"id":76,"isim":"Palm","cinsiyet":"Male","yas":41},
{"id":77,"isim":"Morissa","cinsiyet":"Female","yas":43},
{"id":78,"isim":"Valeria","cinsiyet":"Female","yas":31},
{"id":79,"isim":"Dolph","cinsiyet":"Male","yas":32},
{"id":80,"isim":"Irwinn","cinsiyet":"Male","yas":61},
{"id":81,"isim":"Pam","cinsiyet":"Female","yas":17},
{"id":82,"isim":"Vernon","cinsiyet":"Male","yas":43},
{"id":83,"isim":"Marthe","cinsiyet":"Female","yas":21},
{"id":84,"isim":"Raymund","cinsiyet":"Male","yas":10},
{"id":85,"isim":"Maxi","cinsiyet":"Female","yas":32},
{"id":86,"isim":"Leda","cinsiyet":"Female","yas":28},
{"id":87,"isim":"Paulie","cinsiyet":"Female","yas":39},
{"id":88,"isim":"Abba","cinsiyet":"Male","yas":14},
{"id":89,"isim":"Fanchon","cinsiyet":"Female","yas":69},
{"id":90,"isim":"Osgood","cinsiyet":"Male","yas":65},
{"id":91,"isim":"Jena","cinsiyet":"Female","yas":45},
{"id":92,"isim":"Granville","cinsiyet":"Male","yas":68},
{"id":93,"isim":"Keary","cinsiyet":"Male","yas":45},
{"id":94,"isim":"Karoly","cinsiyet":"Female","yas":47},
{"id":95,"isim":"Steven","cinsiyet":"Male","yas":30},
{"id":96,"isim":"Pauly","cinsiyet":"Male","yas":58},
{"id":97,"isim":"Ingunna","cinsiyet":"Female","yas":57},
{"id":98,"isim":"Hunt","cinsiyet":"Male","yas":47},
{"id":99,"isim":"Emmanuel","cinsiyet":"Male","yas":51},
{"id":100,"isim":"Cedric","cinsiyet":"Male","yas":16},
{"id":101,"isim":"Bernita","cinsiyet":"Female","yas":20},
{"id":102,"isim":"Carey","cinsiyet":"Male","yas":53},
{"id":103,"isim":"Madison","cinsiyet":"Male","yas":64},
{"id":104,"isim":"Dudley","cinsiyet":"Male","yas":66},
{"id":105,"isim":"Meta","cinsiyet":"Female","yas":60},
{"id":106,"isim":"Ginny","cinsiyet":"Female","yas":30},
{"id":107,"isim":"Belvia","cinsiyet":"Female","yas":25},
{"id":108,"isim":"Reinaldos","cinsiyet":"Male","yas":70},
{"id":109,"isim":"Adan","cinsiyet":"Male","yas":68},
{"id":110,"isim":"Lynelle","cinsiyet":"Female","yas":53},
{"id":111,"isim":"Flint","cinsiyet":"Male","yas":22},
{"id":112,"isim":"Melinde","cinsiyet":"Female","yas":27},
{"id":113,"isim":"Paddy","cinsiyet":"Male","yas":17},
{"id":114,"isim":"Leonelle","cinsiyet":"Female","yas":32},
{"id":115,"isim":"Mei","cinsiyet":"Female","yas":31},
{"id":116,"isim":"Panchito","cinsiyet":"Male","yas":69},
{"id":117,"isim":"Saree","cinsiyet":"Female","yas":66},
{"id":118,"isim":"Niki","cinsiyet":"Male","yas":44},
{"id":119,"isim":"Frans","cinsiyet":"Male","yas":48},
{"id":120,"isim":"Sybille","cinsiyet":"Female","yas":69},
{"id":121,"isim":"Sunny","cinsiyet":"Female","yas":28},
{"id":122,"isim":"Ogden","cinsiyet":"Male","yas":65},
{"id":123,"isim":"Weston","cinsiyet":"Male","yas":28},
{"id":124,"isim":"Marcela","cinsiyet":"Female","yas":22},
{"id":125,"isim":"Izabel","cinsiyet":"Female","yas":35},
{"id":126,"isim":"Rheta","cinsiyet":"Female","yas":48},
{"id":127,"isim":"Danielle","cinsiyet":"Female","yas":34},
{"id":128,"isim":"Paige","cinsiyet":"Male","yas":31},
{"id":129,"isim":"Twyla","cinsiyet":"Female","yas":23},
{"id":130,"isim":"Jacques","cinsiyet":"Male","yas":46},
{"id":131,"isim":"Maurizio","cinsiyet":"Male","yas":58},
{"id":132,"isim":"Thor","cinsiyet":"Male","yas":19},
{"id":133,"isim":"Kendre","cinsiyet":"Female","yas":34},
{"id":134,"isim":"Yehudi","cinsiyet":"Male","yas":12},
{"id":135,"isim":"Casar","cinsiyet":"Male","yas":63},
{"id":136,"isim":"Bond","cinsiyet":"Male","yas":56},
{"id":137,"isim":"Georgianna","cinsiyet":"Female","yas":20},
{"id":138,"isim":"Timotheus","cinsiyet":"Male","yas":67},
{"id":139,"isim":"Carroll","cinsiyet":"Female","yas":30},
{"id":140,"isim":"Kimberley","cinsiyet":"Female","yas":19},
{"id":141,"isim":"Lion","cinsiyet":"Male","yas":16},
{"id":142,"isim":"Cleve","cinsiyet":"Male","yas":14},
{"id":143,"isim":"Jackson","cinsiyet":"Male","yas":13},
{"id":144,"isim":"Guthrey","cinsiyet":"Male","yas":36},
{"id":145,"isim":"Stephenie","cinsiyet":"Female","yas":65},
{"id":146,"isim":"Dal","cinsiyet":"Male","yas":36},
{"id":147,"isim":"Godard","cinsiyet":"Male","yas":69},
{"id":148,"isim":"Bailey","cinsiyet":"Male","yas":70},
{"id":149,"isim":"Crissy","cinsiyet":"Female","yas":9},
{"id":150,"isim":"Hildy","cinsiyet":"Female","yas":38},
{"id":151,"isim":"Vincents","cinsiyet":"Male","yas":50},
{"id":152,"isim":"Milicent","cinsiyet":"Female","yas":47},
{"id":153,"isim":"Lisetta","cinsiyet":"Female","yas":67},
{"id":154,"isim":"Roseanna","cinsiyet":"Female","yas":53},
{"id":155,"isim":"Robinet","cinsiyet":"Male","yas":51},
{"id":156,"isim":"Jory","cinsiyet":"Male","yas":48},
{"id":157,"isim":"Bettina","cinsiyet":"Female","yas":42},
{"id":158,"isim":"Wat","cinsiyet":"Male","yas":44},
{"id":159,"isim":"Gerti","cinsiyet":"Female","yas":47},
{"id":160,"isim":"Ilaire","cinsiyet":"Male","yas":15},
{"id":161,"isim":"Caren","cinsiyet":"Female","yas":29},
{"id":162,"isim":"Herbie","cinsiyet":"Male","yas":62},
{"id":163,"isim":"Veriee","cinsiyet":"Female","yas":10},
{"id":164,"isim":"Francesca","cinsiyet":"Female","yas":15},
{"id":165,"isim":"Read","cinsiyet":"Male","yas":53},
{"id":166,"isim":"Correy","cinsiyet":"Female","yas":16},
{"id":167,"isim":"Ferdie","cinsiyet":"Male","yas":40},
{"id":168,"isim":"Marty","cinsiyet":"Female","yas":9},
{"id":169,"isim":"Allyn","cinsiyet":"Male","yas":28},
{"id":170,"isim":"Wrennie","cinsiyet":"Female","yas":28},
{"id":171,"isim":"Free","cinsiyet":"Male","yas":66},
{"id":172,"isim":"Gage","cinsiyet":"Male","yas":45},
{"id":173,"isim":"Flory","cinsiyet":"Male","yas":29},
{"id":174,"isim":"Veronike","cinsiyet":"Female","yas":44},
{"id":175,"isim":"Ker","cinsiyet":"Male","yas":16},
{"id":176,"isim":"Cal","cinsiyet":"Female","yas":24},
{"id":177,"isim":"Nefen","cinsiyet":"Male","yas":39},
{"id":178,"isim":"Olympe","cinsiyet":"Female","yas":35},
{"id":179,"isim":"Stephine","cinsiyet":"Female","yas":19},
{"id":180,"isim":"Geno","cinsiyet":"Male","yas":28},
{"id":181,"isim":"Kynthia","cinsiyet":"Female","yas":30},
{"id":182,"isim":"Bernelle","cinsiyet":"Female","yas":54},
{"id":183,"isim":"Lara","cinsiyet":"Female","yas":66},
{"id":184,"isim":"Zarla","cinsiyet":"Female","yas":50},
{"id":185,"isim":"Quint","cinsiyet":"Male","yas":21},
{"id":186,"isim":"Wilmette","cinsiyet":"Female","yas":41},
{"id":187,"isim":"Annabell","cinsiyet":"Female","yas":41},
{"id":188,"isim":"Rosaline","cinsiyet":"Female","yas":69},
{"id":189,"isim":"Idelle","cinsiyet":"Female","yas":43},
{"id":190,"isim":"Carlos","cinsiyet":"Male","yas":20},
{"id":191,"isim":"Clarence","cinsiyet":"Male","yas":43},
{"id":192,"isim":"Archibaldo","cinsiyet":"Male","yas":43},
{"id":193,"isim":"Katherine","cinsiyet":"Female","yas":61},
{"id":194,"isim":"Caron","cinsiyet":"Female","yas":51},
{"id":195,"isim":"Carling","cinsiyet":"Male","yas":45},
{"id":196,"isim":"Shanda","cinsiyet":"Female","yas":59},
{"id":197,"isim":"Christiano","cinsiyet":"Male","yas":9},
{"id":198,"isim":"Amye","cinsiyet":"Female","yas":52},
{"id":199,"isim":"Lilly","cinsiyet":"Female","yas":47},
{"id":200,"isim":"Claiborn","cinsiyet":"Male","yas":12},
{"id":201,"isim":"Becki","cinsiyet":"Female","yas":66},
{"id":202,"isim":"Wylma","cinsiyet":"Female","yas":49},
{"id":203,"isim":"Audie","cinsiyet":"Female","yas":56},
{"id":204,"isim":"Ogdon","cinsiyet":"Male","yas":12},
{"id":205,"isim":"Suzi","cinsiyet":"Female","yas":29},
{"id":206,"isim":"Ruthy","cinsiyet":"Female","yas":10},
{"id":207,"isim":"Ariadne","cinsiyet":"Female","yas":11},
{"id":208,"isim":"Selle","cinsiyet":"Female","yas":37},
{"id":209,"isim":"Carlie","cinsiyet":"Male","yas":57},
{"id":210,"isim":"Tammy","cinsiyet":"Male","yas":50},
{"id":211,"isim":"Basil","cinsiyet":"Male","yas":12},
{"id":212,"isim":"Phip","cinsiyet":"Male","yas":9},
{"id":213,"isim":"Terrance","cinsiyet":"Male","yas":14},
{"id":214,"isim":"Nollie","cinsiyet":"Female","yas":27},
{"id":215,"isim":"Derick","cinsiyet":"Male","yas":66},
{"id":216,"isim":"Ahmad","cinsiyet":"Male","yas":51},
{"id":217,"isim":"Davidson","cinsiyet":"Male","yas":49},
{"id":218,"isim":"Linell","cinsiyet":"Female","yas":24},
{"id":219,"isim":"Ezechiel","cinsiyet":"Male","yas":43},
{"id":220,"isim":"Helen","cinsiyet":"Female","yas":50},
{"id":221,"isim":"Clim","cinsiyet":"Male","yas":69},
{"id":222,"isim":"Jaquelin","cinsiyet":"Female","yas":9},
{"id":223,"isim":"Washington","cinsiyet":"Male","yas":25},
{"id":224,"isim":"Orly","cinsiyet":"Female","yas":69},
{"id":225,"isim":"Wrennie","cinsiyet":"Female","yas":58},
{"id":226,"isim":"Aliza","cinsiyet":"Female","yas":31},
{"id":227,"isim":"Rozelle","cinsiyet":"Female","yas":16},
{"id":228,"isim":"Rozanna","cinsiyet":"Female","yas":9},
{"id":229,"isim":"Molly","cinsiyet":"Female","yas":44},
{"id":230,"isim":"Carolus","cinsiyet":"Male","yas":15},
{"id":231,"isim":"Langston","cinsiyet":"Male","yas":19},
{"id":232,"isim":"Kelsey","cinsiyet":"Male","yas":17},
{"id":233,"isim":"Britte","cinsiyet":"Female","yas":20},
{"id":234,"isim":"Sansone","cinsiyet":"Male","yas":52},
{"id":235,"isim":"Andy","cinsiyet":"Male","yas":50},
{"id":236,"isim":"Dan","cinsiyet":"Male","yas":29},
{"id":237,"isim":"Dorelle","cinsiyet":"Female","yas":68},
{"id":238,"isim":"Guthrie","cinsiyet":"Male","yas":34},
{"id":239,"isim":"Benoit","cinsiyet":"Male","yas":12},
{"id":240,"isim":"Nissy","cinsiyet":"Female","yas":57},
{"id":241,"isim":"Davidson","cinsiyet":"Male","yas":15},
{"id":242,"isim":"Madelon","cinsiyet":"Female","yas":35},
{"id":243,"isim":"Frederigo","cinsiyet":"Male","yas":63},
{"id":244,"isim":"Daven","cinsiyet":"Male","yas":19},
{"id":245,"isim":"Traci","cinsiyet":"Female","yas":33},
{"id":246,"isim":"Ginelle","cinsiyet":"Female","yas":67},
{"id":247,"isim":"Helena","cinsiyet":"Female","yas":35},
{"id":248,"isim":"Wally","cinsiyet":"Male","yas":35},
{"id":249,"isim":"Mal","cinsiyet":"Male","yas":61},
{"id":250,"isim":"Alf","cinsiyet":"Male","yas":26},
{"id":251,"isim":"Karleen","cinsiyet":"Female","yas":70},
{"id":252,"isim":"Drucy","cinsiyet":"Female","yas":27},
{"id":253,"isim":"Sancho","cinsiyet":"Male","yas":45},
{"id":254,"isim":"Clayton","cinsiyet":"Male","yas":49},
{"id":255,"isim":"Gilberto","cinsiyet":"Male","yas":50},
{"id":256,"isim":"Craig","cinsiyet":"Male","yas":29},
{"id":257,"isim":"Anica","cinsiyet":"Female","yas":38},
{"id":258,"isim":"Lezlie","cinsiyet":"Female","yas":40},
{"id":259,"isim":"Lark","cinsiyet":"Female","yas":37},
{"id":260,"isim":"Mora","cinsiyet":"Female","yas":51},
{"id":261,"isim":"Nicolai","cinsiyet":"Male","yas":50},
{"id":262,"isim":"Lenore","cinsiyet":"Female","yas":45},
{"id":263,"isim":"Austina","cinsiyet":"Female","yas":38},
{"id":264,"isim":"Merna","cinsiyet":"Female","yas":53},
{"id":265,"isim":"Norma","cinsiyet":"Female","yas":43},
{"id":266,"isim":"Raul","cinsiyet":"Male","yas":42},
{"id":267,"isim":"Euell","cinsiyet":"Male","yas":31},
{"id":268,"isim":"Cornall","cinsiyet":"Male","yas":66},
{"id":269,"isim":"Sophey","cinsiyet":"Female","yas":24},
{"id":270,"isim":"Gilles","cinsiyet":"Male","yas":15},
{"id":271,"isim":"Kristian","cinsiyet":"Male","yas":61},
{"id":272,"isim":"Heywood","cinsiyet":"Male","yas":52},
{"id":273,"isim":"Yance","cinsiyet":"Male","yas":30},
{"id":274,"isim":"Isabelle","cinsiyet":"Female","yas":40},
{"id":275,"isim":"Marta","cinsiyet":"Female","yas":41},
{"id":276,"isim":"Becki","cinsiyet":"Female","yas":64},
{"id":277,"isim":"Rickard","cinsiyet":"Male","yas":15},
{"id":278,"isim":"Judy","cinsiyet":"Female","yas":43},
{"id":279,"isim":"Arman","cinsiyet":"Male","yas":25},
{"id":280,"isim":"Ingrim","cinsiyet":"Male","yas":55},
{"id":281,"isim":"Nancey","cinsiyet":"Female","yas":20},
{"id":282,"isim":"Scotty","cinsiyet":"Male","yas":13},
{"id":283,"isim":"Agosto","cinsiyet":"Male","yas":39},
{"id":284,"isim":"Celinka","cinsiyet":"Female","yas":29},
{"id":285,"isim":"Ruthie","cinsiyet":"Female","yas":51},
{"id":286,"isim":"Tyrone","cinsiyet":"Male","yas":55},
{"id":287,"isim":"Terencio","cinsiyet":"Male","yas":53},
{"id":288,"isim":"Anastassia","cinsiyet":"Female","yas":62},
{"id":289,"isim":"Wye","cinsiyet":"Male","yas":61},
{"id":290,"isim":"Prissie","cinsiyet":"Female","yas":39},
{"id":291,"isim":"Mason","cinsiyet":"Male","yas":9},
{"id":292,"isim":"Tammie","cinsiyet":"Female","yas":9},
{"id":293,"isim":"Meyer","cinsiyet":"Male","yas":59},
{"id":294,"isim":"Georgia","cinsiyet":"Female","yas":61},
{"id":295,"isim":"Mark","cinsiyet":"Male","yas":10},
{"id":296,"isim":"Kerstin","cinsiyet":"Female","yas":33},
{"id":297,"isim":"Scotty","cinsiyet":"Male","yas":11},
{"id":298,"isim":"Page","cinsiyet":"Female","yas":10},
{"id":299,"isim":"Sherye","cinsiyet":"Female","yas":41},
{"id":300,"isim":"Charlotta","cinsiyet":"Female","yas":22},
{"id":301,"isim":"Raddie","cinsiyet":"Male","yas":58},
{"id":302,"isim":"Brenda","cinsiyet":"Female","yas":50},
{"id":303,"isim":"Hieronymus","cinsiyet":"Male","yas":46},
{"id":304,"isim":"Babara","cinsiyet":"Female","yas":56},
{"id":305,"isim":"Estella","cinsiyet":"Female","yas":16},
{"id":306,"isim":"Mata","cinsiyet":"Male","yas":25},
{"id":307,"isim":"Bond","cinsiyet":"Male","yas":37},
{"id":308,"isim":"Andres","cinsiyet":"Male","yas":13},
{"id":309,"isim":"Stephannie","cinsiyet":"Female","yas":25},
{"id":310,"isim":"Padget","cinsiyet":"Male","yas":58},
{"id":311,"isim":"Agretha","cinsiyet":"Female","yas":49},
{"id":312,"isim":"Gunilla","cinsiyet":"Female","yas":21},
{"id":313,"isim":"Egon","cinsiyet":"Male","yas":48},
{"id":314,"isim":"Osmond","cinsiyet":"Male","yas":16},
{"id":315,"isim":"Wye","cinsiyet":"Male","yas":37},
{"id":316,"isim":"Benni","cinsiyet":"Female","yas":67},
{"id":317,"isim":"Fiorenze","cinsiyet":"Female","yas":25},
{"id":318,"isim":"Taite","cinsiyet":"Male","yas":16},
{"id":319,"isim":"Sutton","cinsiyet":"Male","yas":46},
{"id":320,"isim":"Lorita","cinsiyet":"Female","yas":14},
{"id":321,"isim":"Chariot","cinsiyet":"Male","yas":58},
{"id":322,"isim":"Augustus","cinsiyet":"Male","yas":50},
{"id":323,"isim":"Adorne","cinsiyet":"Female","yas":24},
{"id":324,"isim":"Wenonah","cinsiyet":"Female","yas":51},
{"id":325,"isim":"Maddie","cinsiyet":"Male","yas":57},
{"id":326,"isim":"Malcolm","cinsiyet":"Male","yas":29},
{"id":327,"isim":"Eilis","cinsiyet":"Female","yas":31},
{"id":328,"isim":"Glenna","cinsiyet":"Female","yas":16},
{"id":329,"isim":"Culley","cinsiyet":"Male","yas":11},
{"id":330,"isim":"Burlie","cinsiyet":"Male","yas":61},
{"id":331,"isim":"Allsun","cinsiyet":"Female","yas":41},
{"id":332,"isim":"Kristina","cinsiyet":"Female","yas":58},
{"id":333,"isim":"Jodie","cinsiyet":"Male","yas":23},
{"id":334,"isim":"Zachariah","cinsiyet":"Male","yas":10},
{"id":335,"isim":"Ruth","cinsiyet":"Female","yas":48},
{"id":336,"isim":"Cullie","cinsiyet":"Male","yas":63},
{"id":337,"isim":"Jameson","cinsiyet":"Male","yas":14},
{"id":338,"isim":"Marris","cinsiyet":"Female","yas":39},
{"id":339,"isim":"Frederica","cinsiyet":"Female","yas":28},
{"id":340,"isim":"Micah","cinsiyet":"Male","yas":20},
{"id":341,"isim":"Linn","cinsiyet":"Male","yas":54},
{"id":342,"isim":"Emilia","cinsiyet":"Female","yas":54},
{"id":343,"isim":"Arther","cinsiyet":"Male","yas":63},
{"id":344,"isim":"Gabriell","cinsiyet":"Female","yas":39},
{"id":345,"isim":"Haskell","cinsiyet":"Male","yas":56},
{"id":346,"isim":"Ora","cinsiyet":"Female","yas":45},
{"id":347,"isim":"Melantha","cinsiyet":"Female","yas":63},
{"id":348,"isim":"Morgana","cinsiyet":"Female","yas":20},
{"id":349,"isim":"Haywood","cinsiyet":"Male","yas":47},
{"id":350,"isim":"Marsh","cinsiyet":"Male","yas":39},
{"id":351,"isim":"Shaina","cinsiyet":"Female","yas":28},
{"id":352,"isim":"Kenneth","cinsiyet":"Male","yas":55},
{"id":353,"isim":"Dud","cinsiyet":"Male","yas":68},
{"id":354,"isim":"Holly","cinsiyet":"Female","yas":14},
{"id":355,"isim":"Olag","cinsiyet":"Male","yas":44},
{"id":356,"isim":"Aloisia","cinsiyet":"Female","yas":45},
{"id":357,"isim":"Carita","cinsiyet":"Female","yas":22},
{"id":358,"isim":"Bryn","cinsiyet":"Female","yas":45},
{"id":359,"isim":"Leonora","cinsiyet":"Female","yas":36},
{"id":360,"isim":"Alair","cinsiyet":"Male","yas":62},
{"id":361,"isim":"Mira","cinsiyet":"Female","yas":16},
{"id":362,"isim":"Skipper","cinsiyet":"Male","yas":52},
{"id":363,"isim":"Cathlene","cinsiyet":"Female","yas":16},
{"id":364,"isim":"Kellen","cinsiyet":"Male","yas":51},
{"id":365,"isim":"Gusta","cinsiyet":"Female","yas":15},
{"id":366,"isim":"Henderson","cinsiyet":"Male","yas":49},
{"id":367,"isim":"Judah","cinsiyet":"Male","yas":67},
{"id":368,"isim":"Harlin","cinsiyet":"Male","yas":47},
{"id":369,"isim":"Isacco","cinsiyet":"Male","yas":13},
{"id":370,"isim":"Jolie","cinsiyet":"Female","yas":62},
{"id":371,"isim":"Reginald","cinsiyet":"Male","yas":52},
{"id":372,"isim":"Billie","cinsiyet":"Female","yas":12},
{"id":373,"isim":"Evelyn","cinsiyet":"Male","yas":41},
{"id":374,"isim":"Bunnie","cinsiyet":"Female","yas":18},
{"id":375,"isim":"Johnny","cinsiyet":"Male","yas":53},
{"id":376,"isim":"Astra","cinsiyet":"Female","yas":70},
{"id":377,"isim":"Murvyn","cinsiyet":"Male","yas":22},
{"id":378,"isim":"Rog","cinsiyet":"Male","yas":59},
{"id":379,"isim":"Ali","cinsiyet":"Female","yas":63},
{"id":380,"isim":"Hayden","cinsiyet":"Male","yas":45},
{"id":381,"isim":"Antin","cinsiyet":"Male","yas":39},
{"id":382,"isim":"James","cinsiyet":"Male","yas":16},
{"id":383,"isim":"Joseito","cinsiyet":"Male","yas":45},
{"id":384,"isim":"Pippa","cinsiyet":"Female","yas":15},
{"id":385,"isim":"Cointon","cinsiyet":"Male","yas":22},
{"id":386,"isim":"Giulia","cinsiyet":"Female","yas":11},
{"id":387,"isim":"Julissa","cinsiyet":"Female","yas":56},
{"id":388,"isim":"Alic","cinsiyet":"Male","yas":48},
{"id":389,"isim":"Suzanne","cinsiyet":"Female","yas":13},
{"id":390,"isim":"Desi","cinsiyet":"Male","yas":28},
{"id":391,"isim":"Tricia","cinsiyet":"Female","yas":14},
{"id":392,"isim":"Row","cinsiyet":"Female","yas":55},
{"id":393,"isim":"Enriqueta","cinsiyet":"Female","yas":24},
{"id":394,"isim":"Wilbert","cinsiyet":"Male","yas":67},
{"id":395,"isim":"Guglielma","cinsiyet":"Female","yas":32},
{"id":396,"isim":"Manda","cinsiyet":"Female","yas":53},
{"id":397,"isim":"Teodora","cinsiyet":"Female","yas":50},
{"id":398,"isim":"Gabriellia","cinsiyet":"Female","yas":62},
{"id":399,"isim":"Doyle","cinsiyet":"Male","yas":70},
{"id":400,"isim":"Corbie","cinsiyet":"Male","yas":39},
{"id":401,"isim":"Rebekah","cinsiyet":"Female","yas":24},
{"id":402,"isim":"Dorry","cinsiyet":"Female","yas":60},
{"id":403,"isim":"Jeno","cinsiyet":"Male","yas":37},
{"id":404,"isim":"Corette","cinsiyet":"Female","yas":63},
{"id":405,"isim":"Malissa","cinsiyet":"Female","yas":61},
{"id":406,"isim":"Vinson","cinsiyet":"Male","yas":25},
{"id":407,"isim":"Chick","cinsiyet":"Male","yas":15},
{"id":408,"isim":"Orin","cinsiyet":"Male","yas":66},
{"id":409,"isim":"Henderson","cinsiyet":"Male","yas":17},
{"id":410,"isim":"Rolfe","cinsiyet":"Male","yas":55},
{"id":411,"isim":"Reggi","cinsiyet":"Female","yas":27},
{"id":412,"isim":"Josy","cinsiyet":"Female","yas":16},
{"id":413,"isim":"Dawna","cinsiyet":"Female","yas":21},
{"id":414,"isim":"Morey","cinsiyet":"Male","yas":45},
{"id":415,"isim":"Kermit","cinsiyet":"Male","yas":22},
{"id":416,"isim":"Ilario","cinsiyet":"Male","yas":11},
{"id":417,"isim":"Bevin","cinsiyet":"Male","yas":24},
{"id":418,"isim":"Una","cinsiyet":"Female","yas":44},
{"id":419,"isim":"Lydon","cinsiyet":"Male","yas":35},
{"id":420,"isim":"Jo","cinsiyet":"Male","yas":9},
{"id":421,"isim":"Cullin","cinsiyet":"Male","yas":22},
{"id":422,"isim":"Hermione","cinsiyet":"Female","yas":52},
{"id":423,"isim":"Granny","cinsiyet":"Male","yas":63},
{"id":424,"isim":"Tiphani","cinsiyet":"Female","yas":42},
{"id":425,"isim":"Far","cinsiyet":"Male","yas":43},
{"id":426,"isim":"Hamish","cinsiyet":"Male","yas":34},
{"id":427,"isim":"Lavinia","cinsiyet":"Female","yas":29},
{"id":428,"isim":"Reynold","cinsiyet":"Male","yas":60},
{"id":429,"isim":"Skell","cinsiyet":"Male","yas":36},
{"id":430,"isim":"Dukey","cinsiyet":"Male","yas":62},
{"id":431,"isim":"Chadwick","cinsiyet":"Male","yas":27},
{"id":432,"isim":"Indira","cinsiyet":"Female","yas":60},
{"id":433,"isim":"Humfried","cinsiyet":"Male","yas":27},
{"id":434,"isim":"Hayley","cinsiyet":"Female","yas":18},
{"id":435,"isim":"Ethelred","cinsiyet":"Male","yas":33},
{"id":436,"isim":"Rolfe","cinsiyet":"Male","yas":54},
{"id":437,"isim":"Erick","cinsiyet":"Male","yas":17},
{"id":438,"isim":"Elvyn","cinsiyet":"Male","yas":43},
{"id":439,"isim":"Jarrod","cinsiyet":"Male","yas":18},
{"id":440,"isim":"Jecho","cinsiyet":"Male","yas":12},
{"id":441,"isim":"Gwenni","cinsiyet":"Female","yas":36},
{"id":442,"isim":"Marcus","cinsiyet":"Male","yas":60},
{"id":443,"isim":"Kerry","cinsiyet":"Female","yas":58},
{"id":444,"isim":"Edgardo","cinsiyet":"Male","yas":63},
{"id":445,"isim":"Gabbey","cinsiyet":"Female","yas":45},
{"id":446,"isim":"Petunia","cinsiyet":"Female","yas":28},
{"id":447,"isim":"Marleah","cinsiyet":"Female","yas":15},
{"id":448,"isim":"Dreddy","cinsiyet":"Female","yas":66},
{"id":449,"isim":"Luciana","cinsiyet":"Female","yas":32},
{"id":450,"isim":"Grange","cinsiyet":"Male","yas":45},
{"id":451,"isim":"Terrel","cinsiyet":"Male","yas":20},
{"id":452,"isim":"My","cinsiyet":"Male","yas":22},
{"id":453,"isim":"Vance","cinsiyet":"Male","yas":62},
{"id":454,"isim":"Ronica","cinsiyet":"Female","yas":37},
{"id":455,"isim":"Glynis","cinsiyet":"Female","yas":61},
{"id":456,"isim":"Ignacio","cinsiyet":"Male","yas":20},
{"id":457,"isim":"Jdavie","cinsiyet":"Male","yas":24},
{"id":458,"isim":"Umeko","cinsiyet":"Female","yas":47},
{"id":459,"isim":"Frederick","cinsiyet":"Male","yas":35},
{"id":460,"isim":"Elsbeth","cinsiyet":"Female","yas":9},
{"id":461,"isim":"Tore","cinsiyet":"Male","yas":10},
{"id":462,"isim":"Amalle","cinsiyet":"Female","yas":44},
{"id":463,"isim":"Carolina","cinsiyet":"Female","yas":24},
{"id":464,"isim":"Andrus","cinsiyet":"Male","yas":29},
{"id":465,"isim":"Jeno","cinsiyet":"Male","yas":44},
{"id":466,"isim":"Aldis","cinsiyet":"Male","yas":49},
{"id":467,"isim":"Melamie","cinsiyet":"Female","yas":42},
{"id":468,"isim":"Elinore","cinsiyet":"Female","yas":45},
{"id":469,"isim":"Camey","cinsiyet":"Male","yas":56},
{"id":470,"isim":"Christian","cinsiyet":"Male","yas":39},
{"id":471,"isim":"Bealle","cinsiyet":"Male","yas":32},
{"id":472,"isim":"Berrie","cinsiyet":"Female","yas":24},
{"id":473,"isim":"Dulsea","cinsiyet":"Female","yas":47},
{"id":474,"isim":"Johan","cinsiyet":"Male","yas":39},
{"id":475,"isim":"Giana","cinsiyet":"Female","yas":41},
{"id":476,"isim":"Griffith","cinsiyet":"Male","yas":70},
{"id":477,"isim":"Elke","cinsiyet":"Female","yas":55},
{"id":478,"isim":"Gusella","cinsiyet":"Female","yas":43},
{"id":479,"isim":"Emmalynn","cinsiyet":"Female","yas":64},
{"id":480,"isim":"Mireille","cinsiyet":"Female","yas":17},
{"id":481,"isim":"Edith","cinsiyet":"Female","yas":23},
{"id":482,"isim":"Wendall","cinsiyet":"Male","yas":63},
{"id":483,"isim":"Turner","cinsiyet":"Male","yas":69},
{"id":484,"isim":"Vonni","cinsiyet":"Female","yas":41},
{"id":485,"isim":"Everard","cinsiyet":"Male","yas":29},
{"id":486,"isim":"Foster","cinsiyet":"Male","yas":41},
{"id":487,"isim":"Cobb","cinsiyet":"Male","yas":15},
{"id":488,"isim":"Manolo","cinsiyet":"Male","yas":41},
{"id":489,"isim":"Huberto","cinsiyet":"Male","yas":35},
{"id":490,"isim":"Craig","cinsiyet":"Male","yas":56},
{"id":491,"isim":"Paige","cinsiyet":"Female","yas":23},
{"id":492,"isim":"Hertha","cinsiyet":"Female","yas":48},
{"id":493,"isim":"Cristabel","cinsiyet":"Female","yas":9},
{"id":494,"isim":"Lyndy","cinsiyet":"Female","yas":29},
{"id":495,"isim":"Becca","cinsiyet":"Female","yas":9},
{"id":496,"isim":"Jeth","cinsiyet":"Male","yas":39},
{"id":497,"isim":"Davina","cinsiyet":"Female","yas":62},
{"id":498,"isim":"Rebe","cinsiyet":"Female","yas":51},
{"id":499,"isim":"Ermanno","cinsiyet":"Male","yas":11},
{"id":500,"isim":"Ericha","cinsiyet":"Female","yas":18}]